sports_prediction_framework/__init__.py
sports_prediction_framework/dataloader/Connector.py
sports_prediction_framework/dataloader/DataLoader.py
sports_prediction_framework/dataloader/DataSource.py
sports_prediction_framework/dataloader/__init__.py
sports_prediction_framework/dataloader/parser/AbstractParser.py
sports_prediction_framework/dataloader/parser/MatchParser.py
sports_prediction_framework/dataloader/parser/RaceParser.py
sports_prediction_framework/dataloader/parser/__init__.py
sports_prediction_framework/datawrapper/DataHandler.py
sports_prediction_framework/datawrapper/DataWrapper.py
sports_prediction_framework/datawrapper/SportType.py
sports_prediction_framework/datawrapper/__init__.py
sports_prediction_framework/datawrapper/sport/LeagueWrapper.py
sports_prediction_framework/datawrapper/sport/MatchWrapper.py
sports_prediction_framework/datawrapper/sport/OddsWrapper.py
sports_prediction_framework/datawrapper/sport/RaceWrapper.py
sports_prediction_framework/datawrapper/sport/__init__.py
sports_prediction_framework/datawrapper/sport/match/AmericanFootballWrapper.py
sports_prediction_framework/datawrapper/sport/match/BaseballWrapper.py
sports_prediction_framework/datawrapper/sport/match/BasketballWrapper.py
sports_prediction_framework/datawrapper/sport/match/FootballWrapper.py
sports_prediction_framework/datawrapper/sport/match/HockeyWrapper.py
sports_prediction_framework/datawrapper/sport/match/__init__.py
sports_prediction_framework/datawrapper/sport/race/CyclingWrapper.py
sports_prediction_framework/datawrapper/sport/race/FormulaOneWrapper.py
sports_prediction_framework/datawrapper/sport/race/GolfWrapper.py
sports_prediction_framework/datawrapper/sport/race/__init__.py
sports_prediction_framework/learner/Learner.py
sports_prediction_framework/learner/Tester.py
sports_prediction_framework/learner/Trainer.py
sports_prediction_framework/learner/__init__.py
sports_prediction_framework/model/FlatModel.py
sports_prediction_framework/model/GNNModel.py
sports_prediction_framework-0.1.4.dist-info/METADATA
sports_prediction_framework-0.1.4.dist-info/WHEEL
sports_prediction_framework-0.1.4.dist-info/top_level.txt
sports_prediction_framework-0.1.4.dist-info/RECORD
