Metadata-Version: 2.4
Name: sports_prediction_framework
Version: 0.1.4
Requires-Dist: mlflow==2.20.2
Requires-Dist: mlflow_skinny==2.20.2
Requires-Dist: numpy<2.0,>=1.18.5
Requires-Dist: optuna==4.3.0
Requires-Dist: pandas==2.2.2
Requires-Dist: paramiko==3.5.1
Requires-Dist: psycopg2_binary==2.9.10
Requires-Dist: python-dotenv==1.1.0
Requires-Dist: scikit_learn==1.6.1
Requires-Dist: setuptools==75.1.0
Requires-Dist: SQLAlchemy==2.0.38
Requires-Dist: sshtunnel==0.4.0
Requires-Dist: torch==2.6.0
Requires-Dist: torch_geometric==2.6.1
Requires-Dist: jedi>=0.16
Requires-Dist: numpy
Dynamic: requires-dist
